finfeatures/indicators.py
finfeatures/init.py
finfeatures/transformers.py
finfeatures/utils.py
finfeatures-0.1.0.dist-info/METADATA
finfeatures-0.1.0.dist-info/WHEEL
finfeatures-0.1.0.dist-info/top_level.txt
finfeatures-0.1.0.dist-info/RECORD
