Metadata-Version: 2.4
Name: finfeatures
Version: 0.1.0
Summary: A simple Financial Feature Engineering library.
Author-email: Advait Dharmadhikari <advaituni@gmail.com>
License: MIT
Classifier: Programming Language :: Python :: 3
Classifier: License :: OSI Approved :: MIT License
Classifier: Operating System :: OS Independent
Classifier: Topic :: Scientific/Engineering :: Information Analysis
Requires-Dist: pandas>=1.0
